<?xml version="1.0" encoding="us-ascii"?>
<SerializableGameEvent xmlns:xsi="http://www.w3.org/2001/XMLSchema-instance" xmlns:xsd="http://www.w3.org/2001/XMLSchema">
  <Containers>
    <Container>
      <Trigger>Interaction</Trigger>
      <Condition>FirstDialogue</Condition>
      <Actions>
        <ActionBase xsi:type="ShowDialogue">
          <Dialogues>
            <Dialogue>
              <Name />
              <ImagePath />
              <Text>Ciao sono un evento di prova</Text>
            </Dialogue>
          </Dialogues>
        </ActionBase>
        <ActionBase xsi:type="MoveCharacter">
          <Distance>5</Distance>
          <Speed>5</Speed>
          <Direction>Left</Direction>
          <ObjectToMove>Leon</ObjectToMove>
        </ActionBase>
      </Actions>
    </Container>
  </Containers>
</SerializableGameEvent>